{
  "UO": {
    "station_name": "Fornells de la Selva",
    "station_code": "UO",
    "periode": "19:00 - 19:30",
    "tm": 12.0,
    "tx": 12.6,
    "tn": 11.4,
    "hr": 58.0,
    "ppt": 0.0
  },
  "XJ": {
    "station_name": "Girona",
    "station_code": "XJ",
    "periode": "19:00 - 19:30",
    "tm": 12.8,
    "tx": 13.1,
    "tn": 12.2,
    "hr": 53.0,
    "ppt": 0.0,
    "vvm": 9.0,
    "dvm": 209.0,
    "vvx": 18.4,
    "pm": 1000.7,
    "rs": 0.0
  },
  "D5": {
    "station_name": "Observatori Fabra",
    "station_code": "D5",
    "periode": "19:00 - 19:30",
    "tm": 10.4,
    "tx": 10.5,
    "tn": 10.3,
    "hr": 63.0,
    "ppt": 0.0,
    "vvm": 24.5,
    "dvm": 250.0,
    "vvx": 38.5,
    "pm": 1002.3,
    "rs": 0.0
  },
  "DP": {
    "station_name": "Das - Aeròdrom",
    "station_code": "DP",
    "periode": "19:00 - 19:30",
    "tm": 4.3,
    "tx": 4.7,
    "tn": 4.0,
    "hr": 70.0,
    "ppt": 0.0,
    "gn": 3.0,
    "vvm": 13.0,
    "dvm": 223.0,
    "vvx": 20.2,
    "pm": 1001.9,
    "rs": 0.0
  },
  "Z3": {
    "station_name": "Malniu a 2.230 m",
    "station_code": "Z3",
    "periode": "19:00 - 19:30",
    "tm": -3.8,
    "tx": -3.7,
    "tn": -4.0,
    "hr": 87.0,
    "ppt": 0.0,
    "gn": 120.0,
    "vvm": 0.7,
    "dvm": 208.0,
    "vvx": 4.0,
    "rs": 0.0
  },
  "DJ": {
    "station_name": "Banyoles",
    "station_code": "DJ",
    "periode": "19:00 - 19:30",
    "tm": 10.5,
    "tx": 11.1,
    "tn": 10.3,
    "hr": 73.0,
    "ppt": 0.0,
    "vvm": 3.2,
    "dvm": 77.0,
    "vvx": 8.3,
    "pm": 1000.5,
    "rs": 0.0
  }
}