{
  "UO": {
    "station_name": "Fornells de la Selva",
    "station_code": "UO",
    "periode": "19:30 - 20:00",
    "tm": 7.5,
    "tx": 7.8,
    "tn": 7.2,
    "hr": 91.0,
    "ppt": 0.0
  },
  "XJ": {
    "station_name": "Girona",
    "station_code": "XJ",
    "periode": "19:30 - 20:00",
    "tm": 8.2,
    "tx": 8.4,
    "tn": 8.0,
    "hr": 91.0,
    "ppt": 0.0,
    "vvm": 1.8,
    "dvm": 274.0,
    "vvx": 5.8,
    "pm": 1008.6,
    "rs": 0.0
  },
  "D5": {
    "station_name": "Observatori Fabra",
    "station_code": "D5",
    "periode": "19:30 - 20:00",
    "tm": 8.8,
    "tx": 9.0,
    "tn": 8.5,
    "hr": 67.0,
    "ppt": 0.0,
    "vvm": 1.4,
    "dvm": 280.0,
    "vvx": 19.1,
    "pm": 1008.8,
    "rs": 0.0
  },
  "DP": {
    "station_name": "Das - Aeròdrom",
    "station_code": "DP",
    "periode": "19:30 - 20:00",
    "tm": 1.3,
    "tx": 2.3,
    "tn": 0.4,
    "hr": 75.0,
    "ppt": 0.0,
    "gn": 0.0,
    "vvm": 2.9,
    "dvm": 161.0,
    "vvx": 11.5,
    "pm": 1011.2,
    "rs": 0.0
  },
  "Z3": {
    "station_name": "Malniu a 2.230 m",
    "station_code": "Z3",
    "periode": "19:30 - 20:00",
    "tm": -0.1,
    "tx": 0.4,
    "tn": -0.3,
    "hr": 76.0,
    "ppt": 0.0,
    "gn": 116.0,
    "vvm": 4.7,
    "dvm": 247.0,
    "vvx": 18.7,
    "rs": 0.0
  },
  "DJ": {
    "station_name": "Banyoles",
    "station_code": "DJ",
    "periode": "19:30 - 20:00",
    "tm": 9.7,
    "tx": 10.0,
    "tn": 9.5,
    "hr": 82.0,
    "ppt": 0.0,
    "vvm": 1.4,
    "dvm": 288.0,
    "vvx": 3.6,
    "pm": 1008.5,
    "rs": 0.0
  }
}