{
  "UO": {
    "station_name": "Fornells de la Selva",
    "station_code": "UO",
    "periode": "11:00 - 11:30",
    "tm": 12.3,
    "tx": 12.8,
    "tn": 12.2,
    "hr": 85.0,
    "ppt": 0.0
  },
  "XJ": {
    "station_name": "Girona",
    "station_code": "XJ",
    "periode": "11:00 - 11:30",
    "tm": 12.0,
    "tx": 12.4,
    "tn": 11.4,
    "hr": 90.0,
    "ppt": 0.0,
    "vvm": 14.4,
    "dvm": 173.0,
    "vvx": 30.6,
    "pm": 1007.8,
    "rs": 406.0
  },
  "DJ": {
    "station_name": "Banyoles",
    "station_code": "DJ",
    "periode": "11:00 - 11:30",
    "tm": 12.3,
    "tx": 12.8,
    "tn": 12.0,
    "hr": 80.0,
    "ppt": 0.0,
    "vvm": 15.5,
    "dvm": 200.0,
    "vvx": 29.2,
    "pm": 1007.3,
    "rs": 447.0
  }
}