{
  "UO": {
    "station_name": "Fornells de la Selva",
    "station_code": "UO",
    "periode": "15:00 - 15:30",
    "tm": 15.0,
    "tx": 15.5,
    "tn": 14.7,
    "hr": 67.0,
    "ppt": 0.0
  },
  "XJ": {
    "station_name": "Girona",
    "station_code": "XJ",
    "periode": "15:00 - 15:30",
    "tm": 16.0,
    "tx": 16.3,
    "tn": 15.5,
    "hr": 62.0,
    "ppt": 0.0,
    "vvm": 13.0,
    "dvm": 204.0,
    "vvx": 29.9,
    "pm": 993.6,
    "rs": 136.0
  },
  "DJ": {
    "station_name": "Banyoles",
    "station_code": "DJ",
    "periode": "15:00 - 15:30",
    "tm": 16.8,
    "tx": 17.1,
    "tn": 16.3,
    "hr": 52.0,
    "ppt": 0.0,
    "vvm": 12.6,
    "dvm": 213.0,
    "vvx": 27.0,
    "pm": 993.0,
    "rs": 163.0
  }
}