{
  "UO": {
    "station_name": "Fornells de la Selva",
    "station_code": "UO",
    "periode": "04:30 - 05:00",
    "tm": 7.9,
    "tx": 8.0,
    "tn": 7.8,
    "hr": 97.0,
    "ppt": 3.5
  },
  "XJ": {
    "station_name": "Girona",
    "station_code": "XJ",
    "periode": "04:30 - 05:00",
    "tm": 7.7,
    "tx": 7.8,
    "tn": 7.6,
    "hr": 100.0,
    "ppt": 3.9,
    "vvm": 10.8,
    "dvm": 356.0,
    "vvx": 26.3,
    "pm": 1014.8,
    "rs": 0.0
  },
  "DJ": {
    "station_name": "Banyoles",
    "station_code": "DJ",
    "periode": "04:30 - 05:00",
    "tm": 7.1,
    "tx": 7.3,
    "tn": 7.0,
    "hr": 100.0,
    "ppt": 4.7,
    "vvm": 20.9,
    "dvm": 356.0,
    "vvx": 39.2,
    "pm": 1015.3,
    "rs": 0.0
  }
}