{
  "UO": {
    "station_name": "Fornells de la Selva",
    "station_code": "UO",
    "periode": "05:00 - 05:30",
    "tm": 7.0,
    "tx": 7.9,
    "tn": 6.3,
    "hr": 80.0,
    "ppt": 0.0
  },
  "XJ": {
    "station_name": "Girona",
    "station_code": "XJ",
    "periode": "05:00 - 05:30",
    "tm": 7.5,
    "tx": 8.1,
    "tn": 7.0,
    "hr": 77.0,
    "ppt": 0.0,
    "vvm": 9.0,
    "dvm": 222.0,
    "vvx": 18.0,
    "pm": 996.0,
    "rs": 0.0
  },
  "DJ": {
    "station_name": "Banyoles",
    "station_code": "DJ",
    "periode": "05:00 - 05:30",
    "tm": 8.8,
    "tx": 10.4,
    "tn": 7.6,
    "hr": 62.0,
    "ppt": 0.0,
    "vvm": 13.3,
    "dvm": 207.0,
    "vvx": 43.2,
    "pm": 994.7,
    "rs": 0.0
  }
}