{
  "UO": {
    "station_name": "Fornells de la Selva",
    "station_code": "UO",
    "periode": "19:30 - 20:00",
    "tm": 7.1,
    "tx": 8.9,
    "tn": 6.3,
    "hr": 74.0,
    "ppt": 0.0
  },
  "XJ": {
    "station_name": "Girona",
    "station_code": "XJ",
    "periode": "19:30 - 20:00",
    "tm": 8.4,
    "tx": 9.6,
    "tn": 7.7,
    "hr": 76.0,
    "ppt": 0.0,
    "vvm": 3.6,
    "dvm": 335.0,
    "vvx": 9.4,
    "pm": 996.9,
    "rs": 0.0
  },
  "DJ": {
    "station_name": "Banyoles",
    "station_code": "DJ",
    "periode": "19:30 - 20:00",
    "tm": 8.5,
    "tx": 9.2,
    "tn": 8.2,
    "hr": 81.0,
    "ppt": 0.0,
    "vvm": 5.8,
    "dvm": 35.0,
    "vvx": 12.6,
    "pm": 996.7,
    "rs": 0.0
  }
}