{
  "UO": {
    "station_name": "Fornells de la Selva",
    "station_code": "UO",
    "periode": "19:30 - 20:00",
    "tm": 7.3,
    "tx": 7.5,
    "tn": 6.8,
    "hr": 88.0,
    "ppt": 0.0
  },
  "XJ": {
    "station_name": "Girona",
    "station_code": "XJ",
    "periode": "19:30 - 20:00",
    "tm": 9.1,
    "tx": 9.2,
    "tn": 8.9,
    "hr": 77.0,
    "ppt": 0.0,
    "vvm": 5.4,
    "dvm": 210.0,
    "vvx": 9.4,
    "pm": 1007.1,
    "rs": 0.0
  },
  "DJ": {
    "station_name": "Banyoles",
    "station_code": "DJ",
    "periode": "19:30 - 20:00",
    "tm": 7.9,
    "tx": 8.1,
    "tn": 7.6,
    "hr": 79.0,
    "ppt": 0.0,
    "vvm": 7.9,
    "dvm": 286.0,
    "vvx": 13.7,
    "pm": 1006.9,
    "rs": 0.0
  }
}