{
  "UO": {
    "station_name": "Fornells de la Selva",
    "station_code": "UO",
    "periode": "14:30 - 15:00",
    "tm": 15.8,
    "tx": 16.1,
    "tn": 15.6,
    "hr": 45.0,
    "ppt": 0.0
  },
  "XJ": {
    "station_name": "Girona",
    "station_code": "XJ",
    "periode": "14:30 - 15:00",
    "tm": 16.9,
    "tx": 17.1,
    "tn": 16.6,
    "hr": 40.0,
    "ppt": 0.0,
    "vvm": 10.4,
    "dvm": 231.0,
    "vvx": 22.0,
    "pm": 999.4,
    "rs": 543.0
  },
  "D5": {
    "station_name": "Observatori Fabra",
    "station_code": "D5",
    "periode": "10:30 - 11:00",
    "tm": 9.4,
    "tx": 9.8,
    "tn": 9.0,
    "hr": 59.0,
    "ppt": 0.0,
    "vvm": 6.5,
    "dvm": 296.0,
    "vvx": 25.9,
    "pm": 1002.7,
    "rs": 413.0
  },
  "DP": {
    "station_name": "Das - Aeròdrom",
    "station_code": "DP",
    "periode": "14:30 - 15:00",
    "tm": 6.4,
    "tx": 7.0,
    "tn": 5.6,
    "hr": 60.0,
    "ppt": 0.0,
    "gn": 1.0,
    "vvm": 20.2,
    "dvm": 221.0,
    "vvx": 32.0,
    "pm": 1000.1,
    "rs": 403.0
  },
  "Z3": {
    "station_name": "Malniu a 2.230 m",
    "station_code": "Z3",
    "periode": "14:30 - 15:00",
    "tm": -3.0,
    "tx": -2.8,
    "tn": -3.3,
    "hr": 71.0,
    "ppt": 0.0,
    "gn": 110.0,
    "vvm": 7.9,
    "dvm": 156.0,
    "vvx": 27.4,
    "rs": 543.0
  },
  "DJ": {
    "station_name": "Banyoles",
    "station_code": "DJ",
    "periode": "14:30 - 15:00",
    "tm": 15.6,
    "tx": 16.0,
    "tn": 15.2,
    "hr": 39.0,
    "ppt": 0.0,
    "vvm": 12.2,
    "dvm": 232.0,
    "vvx": 24.8,
    "pm": 999.2,
    "rs": 488.0
  }
}