{
  "UO": {
    "station_name": "Fornells de la Selva",
    "station_code": "UO",
    "periode": "08:00 - 08:30",
    "tm": 4.0,
    "tx": 4.0,
    "tn": 3.9,
    "hr": 96.0,
    "ppt": 0.5
  },
  "XJ": {
    "station_name": "Girona",
    "station_code": "XJ",
    "periode": "08:00 - 08:30",
    "tm": 4.0,
    "tx": 4.2,
    "tn": 3.9,
    "hr": 99.0,
    "ppt": 1.2,
    "vvm": 2.9,
    "dvm": 321.0,
    "vvx": 5.8,
    "pm": 994.7,
    "rs": 3.0
  },
  "DJ": {
    "station_name": "Banyoles",
    "station_code": "DJ",
    "periode": "08:00 - 08:30",
    "tm": 4.2,
    "tx": 5.0,
    "tn": 3.8,
    "hr": 90.0,
    "ppt": 1.9,
    "vvm": 7.2,
    "dvm": 223.0,
    "vvx": 21.2,
    "pm": 995.0,
    "rs": 1.0
  }
}