{
  "generated_at": "2025-12-29 12:40:23",
  "date_spanish": "29/12/2025",
  "timezone": "UTC",
  "timezone_note": "Les hores estan en UTC. Per hora local: +1h (hivern) o +2h (estiu)",
  "stations": {
    "UO": {
      "station_name": "Fornells de la Selva",
      "date": "2025-12-29",
      "date_spanish": "29/12/2025",
      "last_period": "12:00 - 12:30",
      "last_period_utc": "12:00 - 12:30",
      "updated_at": "12:40",
      "total_periods": 25,
      "max_temp": 11.6,
      "min_temp": 8.9,
      "total_rain": 5.3999999999999995,
      "periods_with_data": {
        "temp_max": 25,
        "temp_min": 25,
        "rain": 25
      },
      "timezone_note": "Les hores estan en UTC (Temps Universal Coordinat). Per obtenir l'hora local, suma 1 hora (hivern) o 2 hores (estiu)."
    },
    "XJ": {
      "station_name": "Girona",
      "date": "2025-12-29",
      "date_spanish": "29/12/2025",
      "last_period": "12:00 - 12:30",
      "last_period_utc": "12:00 - 12:30",
      "updated_at": "12:40",
      "total_periods": 25,
      "max_temp": 12.0,
      "min_temp": 8.6,
      "total_rain": 2.9000000000000004,
      "periods_with_data": {
        "temp_max": 25,
        "temp_min": 25,
        "rain": 25
      },
      "timezone_note": "Les hores estan en UTC (Temps Universal Coordinat). Per obtenir l'hora local, suma 1 hora (hivern) o 2 hores (estiu)."
    }
  }
}